odoo9_addon_partner_contact_nutrition_diet-9.0.1.0.0-py2.7-nspkg.pth
odoo9_addon_partner_contact_nutrition_diet-9.0.1.0.0.dist-info/top_level.txt
odoo9_addon_partner_contact_nutrition_diet-9.0.1.0.0.dist-info/WHEEL
odoo9_addon_partner_contact_nutrition_diet-9.0.1.0.0.dist-info/RECORD
odoo9_addon_partner_contact_nutrition_diet-9.0.1.0.0.dist-info/metadata.json
odoo9_addon_partner_contact_nutrition_diet-9.0.1.0.0.dist-info/DESCRIPTION.rst
odoo9_addon_partner_contact_nutrition_diet-9.0.1.0.0.dist-info/METADATA
odoo9_addon_partner_contact_nutrition_diet-9.0.1.0.0.dist-info/namespace_packages.txt
odoo_addons/partner_contact_nutrition_diet/__openerp__.py
odoo_addons/partner_contact_nutrition_diet/__init__.py
odoo_addons/partner_contact_nutrition_diet/README.rst
odoo_addons/partner_contact_nutrition_diet/security/ir.model.access.csv
odoo_addons/partner_contact_nutrition_diet/models/res_partner.py
odoo_addons/partner_contact_nutrition_diet/models/__init__.py
odoo_addons/partner_contact_nutrition_diet/models/nutrition_diet.py
odoo_addons/partner_contact_nutrition_diet/views/res_partner_view.xml
odoo_addons/partner_contact_nutrition_diet/data/nutrition_diet.xml
odoo_addons/partner_contact_nutrition_diet/static/description/icon.png
